validate_pyproject_schema_store/__init__.py
validate_pyproject_schema_store/py.typed
validate_pyproject_schema_store/schema.py
validate_pyproject_schema_store/resources/black.schema.json
validate_pyproject_schema_store/resources/cibuildwheel.schema.json
validate_pyproject_schema_store/resources/extra.json
validate_pyproject_schema_store/resources/hatch.schema.json
validate_pyproject_schema_store/resources/maturin.schema.json
validate_pyproject_schema_store/resources/mypy.schema.json
validate_pyproject_schema_store/resources/partial-pdm-dockerize.schema.json
validate_pyproject_schema_store/resources/pdm.schema.json
validate_pyproject_schema_store/resources/poe.schema.json
validate_pyproject_schema_store/resources/poetry.schema.json
validate_pyproject_schema_store/resources/pyright.schema.json
validate_pyproject_schema_store/resources/pytest.schema.json
validate_pyproject_schema_store/resources/repo-review.schema.json
validate_pyproject_schema_store/resources/ruff.schema.json
validate_pyproject_schema_store/resources/scikit-build.schema.json
validate_pyproject_schema_store/resources/setuptools.schema.json
validate_pyproject_schema_store/resources/setuptools_scm.schema.json
validate_pyproject_schema_store/resources/taskipy.schema.json
validate_pyproject_schema_store/resources/tombi.schema.json
validate_pyproject_schema_store/resources/tool.json
validate_pyproject_schema_store/resources/tox.schema.json
validate_pyproject_schema_store/resources/ty.schema.json
validate_pyproject_schema_store/resources/uv.schema.json
validate_pyproject_schema_store-2026.1.22.dist-info/METADATA
validate_pyproject_schema_store-2026.1.22.dist-info/WHEEL
validate_pyproject_schema_store-2026.1.22.dist-info/entry_points.txt
validate_pyproject_schema_store-2026.1.22.dist-info/licenses/LICENSE
validate_pyproject_schema_store-2026.1.22.dist-info/RECORD
