Metadata-Version: 2.4
Name: validate-pyproject-schema-store
Version: 2026.1.22
Summary: A plugin set for validate-pyproject and schema-store.
Project-URL: Homepage, https://github.com/henryiii/validate-pyproject-schema-store
Project-URL: Bug Tracker, https://github.com/henryiii/validate-pyproject-schema-store/issues
Project-URL: Discussions, https://github.com/henryiii/validate-pyproject-schema-store/discussions
Project-URL: Changelog, https://github.com/henryiii/validate-pyproject-schema-store/releases
Author-email: Henry Schreiner <henryfs@princeton.edu>
License-File: LICENSE
Classifier: Development Status :: 4 - Beta
Classifier: Intended Audience :: Developers
Classifier: License :: OSI Approved :: Apache Software License
Classifier: Operating System :: OS Independent
Classifier: Programming Language :: Python
Classifier: Programming Language :: Python :: 3
Classifier: Programming Language :: Python :: 3 :: Only
Classifier: Programming Language :: Python :: 3.8
Classifier: Programming Language :: Python :: 3.9
Classifier: Programming Language :: Python :: 3.10
Classifier: Programming Language :: Python :: 3.11
Classifier: Programming Language :: Python :: 3.12
Classifier: Programming Language :: Python :: 3.13
Classifier: Programming Language :: Python :: 3.14
Classifier: Topic :: Software Development :: Quality Assurance
Classifier: Typing :: Typed
Requires-Python: >=3.8
Requires-Dist: importlib-resources; python_version < '3.9'
Provides-Extra: all
Requires-Dist: validate-pyproject[all]; extra == 'all'
Provides-Extra: validate-pyproject
Requires-Dist: validate-pyproject; extra == 'validate-pyproject'
